LICENSE
README.rst
assert.cpp
bind.cpp
cloudi.cpp
cloudi.py
cloudi_c.py
cloudi_py.cpp
setup.cfg
setup.py
timer.cpp
cloudi.egg-info/PKG-INFO
cloudi.egg-info/SOURCES.txt
cloudi.egg-info/dependency_links.txt
cloudi.egg-info/requires.txt
cloudi.egg-info/top_level.txt