Metadata-Version: 2.1
Name: cloudi
Version: 2.0.6
Summary: Python CloudI API
Home-page: https://cloudi.org
Author: Michael Truog
Author-email: mjtruog@protonmail.com
License: MIT
Platform: UNKNOWN
Classifier: Development Status :: 5 - Production/Stable
Classifier: Intended Audience :: Developers
Classifier: License :: OSI Approved :: MIT License
Classifier: Operating System :: OS Independent
Classifier: Operating System :: POSIX :: BSD
Classifier: Operating System :: POSIX :: Linux
Classifier: Operating System :: Unix
Classifier: Programming Language :: Python
Classifier: Programming Language :: Python :: 3
Classifier: Topic :: Software Development :: Libraries :: Application Frameworks
Classifier: Topic :: System :: Clustering
Classifier: Topic :: System :: Distributed Computing
